pywe_oauth/__init__.py
pywe_oauth/oauth.py
pywe_oauth-1.1.2.dist-info/METADATA
pywe_oauth-1.1.2.dist-info/WHEEL
pywe_oauth-1.1.2.dist-info/top_level.txt
pywe_oauth-1.1.2.dist-info/RECORD
