Metadata-Version: 2.1
Name: pywe-oauth
Version: 1.1.2
Summary: Wechat Oauth Module for Python.
Home-page: https://github.com/sdkwe/pywe-oauth
Author: Hackathon
Author-email: kimi.huang@brightcells.com
Keywords: Wechat Weixin Oauth Oauth2
Classifier: License :: OSI Approved :: BSD License
Classifier: Programming Language :: Python
Classifier: Programming Language :: Python :: 2
Classifier: Programming Language :: Python :: 2.6
Classifier: Programming Language :: Python :: 2.7
Classifier: Programming Language :: Python :: 3
Classifier: Programming Language :: Python :: 3.2
Classifier: Programming Language :: Python :: 3.3
Classifier: Programming Language :: Python :: 3.4
Classifier: Topic :: Software Development :: Libraries :: Python Modules
Requires-Dist: pywe-base (>=1.0.7)
Requires-Dist: shortuuid
Requires-Dist: six
